wj_common/common/commons_function.py
wj_common/utils/utils.py
wj_exception/exception/no_data.py
wj_exception/exception/request.py
wj_exception/exception/unauthorized.py
wj_exception/exception/utils/__init__.py
wj_exception/exception/utils/utils.py
wj_utilities-0.1.0.dist-info/LICENSE.md
wj_utilities-0.1.0.dist-info/WHEEL
wj_utilities-0.1.0.dist-info/METADATA
wj_utilities-0.1.0.dist-info/RECORD
