Metadata-Version: 2.1
Name: wj-utilities
Version: 0.1.0
Summary: library for handle custom exception and commons functionalities for W&J micro services
License: GNU GENERAL PUBLIC LICENSE Version 3, 29 June 2007
Keywords: exceptions,common functions
Author: Jose Arroyave
Author-email: josearroyave@whaleandjaguar.com
Requires-Python: >=3.8,<3.10
Classifier: License :: Other/Proprietary License
Classifier: Programming Language :: Python :: 3
Classifier: Programming Language :: Python :: 3.8
Classifier: Programming Language :: Python :: 3.9
